MANIFEST.in
README.md
setup.py
music2storage/__init__.py
music2storage/connection.py
music2storage/helpers.py
music2storage/service.py
music2storage/signalhandler.py
music2storage/worker.py
music2storage.egg-info/PKG-INFO
music2storage.egg-info/SOURCES.txt
music2storage.egg-info/dependency_links.txt
music2storage.egg-info/not-zip-safe
music2storage.egg-info/requires.txt
music2storage.egg-info/top_level.txt