Metadata-Version: 1.2
Name: music2storage
Version: 0.1.5
Summary: Downloads music from a service and stores it in a cloud or local storage.
Home-page: https://github.com/Music-Moo/music2storage
Author: Radu Raicea
Author-email: radu@raicea.com
License: GPLv3
Platform: UNKNOWN
Requires-Python: >=3.6
